easy_whisper_local/__init__.py
easy_whisper_local/base.py
easy_whisper_local/streaming.py
easy_whisper_local-1.2.5.dist-info/METADATA
easy_whisper_local-1.2.5.dist-info/WHEEL
easy_whisper_local-1.2.5.dist-info/top_level.txt
easy_whisper_local-1.2.5.dist-info/RECORD
