Metadata-Version: 2.1
Name: easy-whisper-local
Version: 1.2.5
Requires-Dist: openai-whisper
Requires-Dist: numpy
